dl621
