Metadata-Version: 2.1
Name: dl621
Version: 2.0.0
Summary: A simple python module and CLI utility to download e621 images with embedded XMP tags and description
Home-page: https://github.com/nimaid/python-dl621
Author: Ella Jameson
Author-email: ellagjameson@gmail.com
License: Copyright (c) 2022, Ella Jameson
Platform: UNKNOWN
License-File: LICENSE
